django_rotating_backup/__init__.py
django_rotating_backup/backup.py
django_rotating_backup/exceptions.py
django_rotating_backup/management/__init__.py
django_rotating_backup/management/commands/__init__.py
django_rotating_backup/management/commands/create_backup.py
django_rotating_backup-1.0.1.dist-info/LICENSE.txt
django_rotating_backup-1.0.1.dist-info/METADATA
django_rotating_backup-1.0.1.dist-info/WHEEL
django_rotating_backup-1.0.1.dist-info/top_level.txt
django_rotating_backup-1.0.1.dist-info/RECORD
