Metadata-Version: 2.1
Name: django-rotating-backup
Version: 1.0.1
Summary: A simple Django app to make rotating backups of the Django database and media files.
Home-page: https://github.com/erikdewildt/django-rotating-backup
Author: erik.de.wildt
Author-email: erik.de.wildt@gmail.com
License: GNU GENERAL PUBLIC LICENSE
Platform: UNKNOWN
Classifier: Development Status :: 5 - Production/Stable
Classifier: Environment :: Web Environment
Classifier: Framework :: Django
Classifier: Intended Audience :: Developers
Classifier: License :: OSI Approved :: GNU General Public License v3 or later (GPLv3+)
Classifier: Operating System :: OS Independent
Classifier: Programming Language :: Python
Classifier: Programming Language :: Python :: 3
Classifier: Topic :: Internet :: WWW/HTTP
Classifier: Topic :: Internet :: WWW/HTTP :: Dynamic Content
Classifier: Topic :: System :: Archiving :: Backup
